AUTHORS
CHANGELOG.rst
LICENSE
MANIFEST.in
README
README.rst
requirements.txt
setup.cfg
setup.py
docs/CHANGELOG.rst
docs/CONTRIBUTING.rst
docs/LICENSE.rst
docs/README.rst
docs/conf.py
docs/index.rst
docs/html/index.html
pydistman/__init__.py
pydistman/__main__.py
pydistman/template.py
pydistman.egg-info/PKG-INFO
pydistman.egg-info/SOURCES.txt
pydistman.egg-info/dependency_links.txt
pydistman.egg-info/entry_points.txt
pydistman.egg-info/not-zip-safe
pydistman.egg-info/requires.txt
pydistman.egg-info/top_level.txt
tests/__init__.py
tests/test_sanity.py
tests/test_use.py