Metadata-Version: 2.1
Name: pydistman
Version: 0.0.10
Summary: "Maximum Overkill DRY" PyPI distribution manager (WiP)
Home-page: https://github.com/shlomif/pydistman
Author: Shlomi Fish
Author-email: shlomif@cpan.org
License: 3-clause BSD
Keywords: pydistman
Platform: any
Classifier: Development Status :: 1 - Planning
Classifier: Programming Language :: Python
Classifier: Programming Language :: Python :: 3
Classifier: Programming Language :: Python :: 3.6
Classifier: Programming Language :: Python :: 3.7
Classifier: Programming Language :: Python :: 3.8
Classifier: Programming Language :: Python :: 3.9
Classifier: Programming Language :: Python :: 3.10
Classifier: Programming Language :: Python :: 3.11
License-File: LICENSE
License-File: AUTHORS
